README
setup.cfg
setup.py
pymachine/__init__.py
pymachine/condition.py
pymachine/exceptions.py
pymachine/state_machine.py
pymachine/transition_table.py
pymachine.egg-info/PKG-INFO
pymachine.egg-info/SOURCES.txt
pymachine.egg-info/dependency_links.txt
pymachine.egg-info/top_level.txt