Metadata-Version: 1.0
Name: pymachine
Version: 0.1.0
Summary: Package for creating state machines.
Home-page: https://github.com/landrew31/pymachine
Author: Andriy Lupa
Author-email: lupaandriy31@gmail.com
License: UNKNOWN
Keywords: state,machine,state machine,automaton
Platform: UNKNOWN
